odoo10_addon_stock_location_restrict_procurement_group-10.0.1.1.1-py3.8-nspkg.pth
odoo/addons/stock_location_restrict_procurement_group/README.rst
odoo/addons/stock_location_restrict_procurement_group/__init__.py
odoo/addons/stock_location_restrict_procurement_group/__manifest__.py
odoo/addons/stock_location_restrict_procurement_group/hooks.py
odoo/addons/stock_location_restrict_procurement_group/i18n/stock_location_restrict_procurement_group.pot
odoo/addons/stock_location_restrict_procurement_group/models/__init__.py
odoo/addons/stock_location_restrict_procurement_group/models/stock_location.py
odoo/addons/stock_location_restrict_procurement_group/models/stock_move.py
odoo/addons/stock_location_restrict_procurement_group/models/stock_pack_operation.py
odoo/addons/stock_location_restrict_procurement_group/models/stock_picking.py
odoo/addons/stock_location_restrict_procurement_group/static/description/icon.png
odoo/addons/stock_location_restrict_procurement_group/tests/__init__.py
odoo/addons/stock_location_restrict_procurement_group/tests/test_stock_location_restrict_group.py
odoo/addons/stock_location_restrict_procurement_group/views/stock_location.xml
odoo/addons/stock_location_restrict_procurement_group/views/stock_move.xml
odoo10_addon_stock_location_restrict_procurement_group-10.0.1.1.1.dist-info/METADATA
odoo10_addon_stock_location_restrict_procurement_group-10.0.1.1.1.dist-info/WHEEL
odoo10_addon_stock_location_restrict_procurement_group-10.0.1.1.1.dist-info/namespace_packages.txt
odoo10_addon_stock_location_restrict_procurement_group-10.0.1.1.1.dist-info/top_level.txt
odoo10_addon_stock_location_restrict_procurement_group-10.0.1.1.1.dist-info/RECORD
